pycoreutil/__init__.py
pycoreutil/dateutils.py
pycoreutil/pathutils.py
pycoreutil-2.1.0.dist-info/License.txt
pycoreutil-2.1.0.dist-info/METADATA
pycoreutil-2.1.0.dist-info/WHEEL
pycoreutil-2.1.0.dist-info/top_level.txt
pycoreutil-2.1.0.dist-info/RECORD
