Metadata-Version: 2.1
Name: pycoreutil
Version: 2.1.0
Summary: Description
Home-page: https://github.com/robertkimts/pycoreutil
Author: robert kimts
Author-email: robertkimts@outlook.com
License: License
License-File: License.txt
